tweet_model/__init__.py
tweet_model/cli.py
tweet_model/tweet.py
tweet_model/utils.py
tweet_model_serpucga-0.7.3.dist-info/AUTHORS.rst
tweet_model_serpucga-0.7.3.dist-info/LICENSE
tweet_model_serpucga-0.7.3.dist-info/METADATA
tweet_model_serpucga-0.7.3.dist-info/WHEEL
tweet_model_serpucga-0.7.3.dist-info/entry_points.txt
tweet_model_serpucga-0.7.3.dist-info/top_level.txt
tweet_model_serpucga-0.7.3.dist-info/RECORD
