Metadata-Version: 2.1
Name: tweet-model-serpucga
Version: 0.7.3
Summary: A modelization of a tweet object with convenient features and functionalities
Home-page: https://gitlab.com/Serbaf/tweet-model-serpucga
Author: Sergio Puche García
Author-email: serpucga@protonmail.com
License: MIT license
Keywords: tweet_model
Platform: UNKNOWN
Classifier: Development Status :: 2 - Pre-Alpha
Classifier: Intended Audience :: Developers
Classifier: License :: OSI Approved :: MIT License
Classifier: Natural Language :: English
Classifier: Programming Language :: Python :: 3
Classifier: Programming Language :: Python :: 3.4
Classifier: Programming Language :: Python :: 3.5
Classifier: Programming Language :: Python :: 3.6
Classifier: Programming Language :: Python :: 3.7
Classifier: Programming Language :: Python :: 3.8
Classifier: Programming Language :: Python :: 3.9
Requires-Dist: Click (>=6.0)
Requires-Dist: tweetmanager-serpucga (>=1.1.0)
